nc_py_api/__init__.py
nc_py_api/_deffered_error.py
nc_py_api/_exceptions.py
nc_py_api/_misc.py
nc_py_api/_preferences.py
nc_py_api/_preferences_ex.py
nc_py_api/_session.py
nc_py_api/_talk_api.py
nc_py_api/_theming.py
nc_py_api/_version.py
nc_py_api/activity.py
nc_py_api/apps.py
nc_py_api/calendar_api.py
nc_py_api/loginflow_v2.py
nc_py_api/nextcloud.py
nc_py_api/notes.py
nc_py_api/notifications.py
nc_py_api/options.py
nc_py_api/talk.py
nc_py_api/talk_bot.py
nc_py_api/user_status.py
nc_py_api/users.py
nc_py_api/users_groups.py
nc_py_api/weather_status.py
nc_py_api/webhooks.py
nc_py_api/ex_app/__init__.py
nc_py_api/ex_app/defs.py
nc_py_api/ex_app/integration_fastapi.py
nc_py_api/ex_app/logger.py
nc_py_api/ex_app/misc.py
nc_py_api/ex_app/occ_commands.py
nc_py_api/ex_app/persist_transformers_cache.py
nc_py_api/ex_app/uvicorn_fastapi.py
nc_py_api/ex_app/providers/__init__.py
nc_py_api/ex_app/providers/providers.py
nc_py_api/ex_app/providers/task_processing.py
nc_py_api/ex_app/ui/__init__.py
nc_py_api/ex_app/ui/files_actions.py
nc_py_api/ex_app/ui/resources.py
nc_py_api/ex_app/ui/settings.py
nc_py_api/ex_app/ui/top_menu.py
nc_py_api/ex_app/ui/ui.py
nc_py_api/files/__init__.py
nc_py_api/files/_files.py
nc_py_api/files/files.py
nc_py_api/files/files_async.py
nc_py_api/files/sharing.py
nc_py_api-0.22.0.dist-info/METADATA
nc_py_api-0.22.0.dist-info/WHEEL
nc_py_api-0.22.0.dist-info/licenses/AUTHORS
nc_py_api-0.22.0.dist-info/licenses/LICENSE.txt
nc_py_api-0.22.0.dist-info/RECORD
