Metadata-Version: 2.4
Name: nc-py-api
Version: 0.22.0
Summary: Nextcloud Python Framework
Project-URL: Changelog, https://github.com/cloud-py-api/nc_py_api/blob/main/CHANGELOG.md
Project-URL: Documentation, https://cloud-py-api.github.io/nc_py_api/
Project-URL: Source, https://github.com/cloud-py-api/nc_py_api
Author-email: Alexander Piskun <bigcat88@icloud.com>
License-Expression: BSD-3-Clause
License-File: AUTHORS
License-File: LICENSE.txt
Keywords: api,client,framework,library,nextcloud
Classifier: Development Status :: 4 - Beta
Classifier: Intended Audience :: Developers
Classifier: License :: OSI Approved :: BSD License
Classifier: Operating System :: MacOS :: MacOS X
Classifier: Operating System :: Microsoft :: Windows
Classifier: Operating System :: POSIX :: Linux
Classifier: Programming Language :: Python :: 3 :: Only
Classifier: Programming Language :: Python :: 3.10
Classifier: Programming Language :: Python :: 3.11
Classifier: Programming Language :: Python :: 3.12
Classifier: Programming Language :: Python :: 3.13
Classifier: Programming Language :: Python :: Implementation :: CPython
Classifier: Programming Language :: Python :: Implementation :: PyPy
Classifier: Topic :: Internet :: WWW/HTTP
Classifier: Topic :: Internet :: WWW/HTTP :: Dynamic Content
Classifier: Topic :: Software Development
Classifier: Topic :: Software Development :: Libraries
Classifier: Topic :: Software Development :: Libraries :: Application Frameworks
Classifier: Topic :: Software Development :: Libraries :: Python Modules
Requires-Python: >=3.10
Requires-Dist: fastapi>=0.109.2
Requires-Dist: niquests<4,>=3
Requires-Dist: pydantic>=2.1.1
Requires-Dist: python-dotenv>=1
Requires-Dist: xmltodict>=0.13
Provides-Extra: app
Requires-Dist: uvicorn[standard]>=0.23.2; extra == 'app'
Provides-Extra: bench
Requires-Dist: matplotlib; extra == 'bench'
Requires-Dist: numpy; extra == 'bench'
Requires-Dist: py-cpuinfo; extra == 'bench'
Requires-Dist: uvicorn[standard]>=0.23.2; extra == 'bench'
Provides-Extra: calendar
Requires-Dist: caldav==1.3.6; extra == 'calendar'
Provides-Extra: dev
Requires-Dist: caldav==1.3.6; extra == 'dev'
Requires-Dist: coverage; extra == 'dev'
Requires-Dist: huggingface-hub; extra == 'dev'
Requires-Dist: matplotlib; extra == 'dev'
Requires-Dist: numpy; extra == 'dev'
Requires-Dist: pillow; extra == 'dev'
Requires-Dist: pre-commit; extra == 'dev'
Requires-Dist: py-cpuinfo; extra == 'dev'
Requires-Dist: pylint; extra == 'dev'
Requires-Dist: pytest; extra == 'dev'
Requires-Dist: pytest-asyncio; extra == 'dev'
Requires-Dist: uvicorn[standard]>=0.23.2; extra == 'dev'
Provides-Extra: dev-min
Requires-Dist: coverage; extra == 'dev-min'
Requires-Dist: huggingface-hub; extra == 'dev-min'
Requires-Dist: pillow; extra == 'dev-min'
Requires-Dist: pre-commit; extra == 'dev-min'
Requires-Dist: pylint; extra == 'dev-min'
Requires-Dist: pytest; extra == 'dev-min'
Requires-Dist: pytest-asyncio; extra == 'dev-min'
Provides-Extra: docs
Requires-Dist: autodoc-pydantic>=2.0.1; extra == 'docs'
Requires-Dist: caldav==1.3.6; extra == 'docs'
Requires-Dist: sphinx-copybutton; extra == 'docs'
Requires-Dist: sphinx-inline-tabs; extra == 'docs'
Requires-Dist: sphinx-issues>=3.0.1; extra == 'docs'
Requires-Dist: sphinx-rtd-theme<3; extra == 'docs'
Requires-Dist: sphinx<8; extra == 'docs'
Requires-Dist: uvicorn[standard]>=0.23.2; extra == 'docs'
